numpymaxflowcpp.cp39-win_amd64.pyd
numpymaxflow/__init__.py
numpymaxflow-0.0.7.dist-info/LICENSE
numpymaxflow-0.0.7.dist-info/METADATA
numpymaxflow-0.0.7.dist-info/WHEEL
numpymaxflow-0.0.7.dist-info/top_level.txt
numpymaxflow-0.0.7.dist-info/RECORD
