Metadata-Version: 2.1
Name: numpymaxflow
Version: 0.0.7
Summary: numpymaxflow: Max-flow/Min-cut in Numpy for 2D images and 3D volumes
Home-page: https://github.com/masadcv/numpymaxflow
Author: Muhammad Asad
Author-email: masadcv@gmail.com
License: BSD-3-Clause License
Classifier: License :: OSI Approved :: BSD License
Classifier: Programming Language :: Python :: 3
Requires-Python: >=3.9
License-File: LICENSE
